ryo3/__init__.py
ryo3/py.typed
ryo3-0.0.1.dist-info/METADATA
ryo3-0.0.1.dist-info/WHEEL
ryo3-0.0.1.dist-info/licenses/LICENSE-APACHE
ryo3-0.0.1.dist-info/licenses/LICENSE-MIT
ryo3-0.0.1.dist-info/RECORD
