Metadata-Version: 2.4
Name: ryo3
Version: 0.0.1
Summary: ryo3 - python package
Author-email: jessekrubin <jessekrubin@gmail.com>
License-File: LICENSE-APACHE
License-File: LICENSE-MIT
Requires-Python: >=3.9
